{
    "social": {
        "blog": "https://www.instagram.com/xartistsclub",
        "twitter": "https://twitter.com/tudurioriginal",
        "whitepaper": "https://xartists.gitbook.io/xartists/"
    },
    "website": "https://linktr.ee/xartists",
    "description": "The first xArtists fundraising dedicated to the art gallery co-ownership with the xArtists 1991 NFT collection. Each NFT allows Access to the \"co-property ownership\" concept.\nThe benefits of the ICO include, monthly staking\nrewards, airdrop of NFTs and a percentage of sales of physicals or NFTs. All sales\nwill be redistributed according to the business plan redistribution\n",
    "status": "active"
}