{
    "social": {
        "blog": "https://t.me/XperienceClubPoker"
    },
    "website": "https://x.com/XperiencePoker",
    "description": "The $PXC token, meticulously designed for the #MultiversX ecosystem, caters specifically to the poker enthusiast community, providing a unique blend of utility, entertainment, and community engagement. With a focus on user experience and innovation, the $PXC token aims to bridge the gap between traditional poker and the digital realm! Are you all in?",
    "status": "active"
}