{
  "website": "https://erms.ro",
  "description": "ERMS token is used for Gameplay rewards, NFT Purchase, Gameplay entry fees, Staking. ERMS host events that generates revenue for winners.",
  "ledgerSignature": "",
  "social": {
    "email": "support@erms.ro",
    "blog": "https://www.erms.ro",
    "twitter": "https://twitter.com/erms_ro",
    "whitepaper": "https://www.aerovek.com/summary/",
    "instagram": "https://instagram.com/erms.ro",
    "tiktok": "https://tiktok.com/@erms.ro",
    "facebook": "https://facebook.com/erms.ro",
    "telegram": "https://t.me/ermsannouncements",
    "coinmarketcap": "",
    "coingecko": ""
  },
  "status": "active"
}