{
"website": "https://www.hodl-token.club",
"description": "$HODL is very fist token on Elrond Network distributed leveraging NFT tech. $HODL acts as a share of Hodl Token Club net worth and NFT's utility is to reward hodlers on daily basis.",
"ledgerSignature": "",
"social": {
"email": "hodl.token.club@gmail.com",
"twitter": "https://https://twitter.com/HodlTokenClub",
"whitepaper": "https://drive.google.com/file/d/1H4KJ1Fl0lrQRyJ6xPUSymlz_YnncCCLc/view?usp=sharing",
"discord": "https://discord.gg/bNfsrgmnzR",
"telegram": "https://t.me/HodlClubCommunity",
"status": "active"
}
